{
  "titre": "Taux de pénétration Internet par pays (Estimations 2026)",
  "unite": "Pourcentage de la population",
  "donnees": [
    { "rang": 1, "pays": "Émirats Arabes Unis", "taux": 100.0, "observations": "Leader mondial grâce à une infrastructure ultra-moderne." },
    { "rang": 2, "pays": "Arabie Saoudite", "taux": 100.0, "observations": "Forte poussée liée au plan Vision 2030." },
    { "rang": 3, "pays": "Bahreïn", "taux": 100.0, "observations": "État totalement fibré et couvert en 5G." },
    { "rang": 4, "pays": "Islande", "taux": 99.4, "observations": "Connectivité quasi-totale malgré une géographie difficile." },
    { "rang": 5, "pays": "Koweït", "taux": 99.3, "observations": "Digitalisation massive des services publics." },
    { "rang": 6, "pays": "Luxembourg", "taux": 99.2, "observations": "Hub financier européen entièrement connecté." },
    { "rang": 7, "pays": "Danemark", "taux": 99.0, "observations": "Champion de la dématérialisation administrative." },
    { "rang": 8, "pays": "Norvège", "taux": 98.8, "observations": "Accès haut débit garanti même dans les fjords." },
    { "rang": 9, "pays": "Pays-Bas", "taux": 98.6, "observations": "L'un des réseaux les plus denses d'Europe." },
    { "rang": 10, "pays": "Corée du Sud", "taux": 97.8, "observations": "Société la plus intégrée au numérique (vie quotidienne)." },
    { "rang": 11, "pays": "Suisse", "taux": 98.4, "observations": "Infrastructures de pointe et usage pro intensif." },
    { "rang": 12, "pays": "Royaume-Uni", "taux": 98.2, "observations": "Très fort taux d'équipement mobile et e-commerce." },
    { "rang": 13, "pays": "Suède", "taux": 98.1, "observations": "Pionnier de la 'société sans cash' et du télétravail." },
    { "rang": 14, "pays": "Canada", "taux": 97.9, "observations": "Record de temps passé : usage massif du streaming." },
    { "rang": 15, "pays": "Finlande", "taux": 97.5, "observations": "Droit à l'Internet haut débit inscrit dans la loi." },
    { "rang": 16, "pays": "Singapour", "taux": 97.1, "observations": "Hub technologique, mais légère fracture chez les seniors." },
    { "rang": 17, "pays": "Belgique", "taux": 96.5, "observations": "Modernisation rapide des réseaux câblés et fibre." },
    { "rang": 18, "pays": "France", "taux": 96.2, "observations": "Succès de la fibre : plan France Très Haut Débit réussi." },
    { "rang": 19, "pays": "Allemagne", "taux": 95.8, "observations": "Retard historique sur la fibre désormais presque comblé." },
    { "rang": 20, "pays": "États-Unis", "taux": 95.3, "observations": "Disparités rurales compensées par le satellite (Starlink)." },
    { "rang": 21, "pays": "Espagne", "taux": 94.9, "observations": "Leader européen sur la vitesse moyenne de la fibre." },
    { "rang": 22, "pays": "Autriche", "taux": 94.5, "observations": "Digitalisation poussée du secteur touristique et alpin." },
    { "rang": 23, "pays": "Australie", "taux": 94.2, "observations": "Dépendance totale au numérique pour pallier les distances." },
    { "rang": 24, "pays": "Israël", "taux": 93.8, "observations": "'Start-up Nation' avec une culture mobile omniprésente." },
    { "rang": 25, "pays": "Estonie", "taux": 93.5, "observations": "Administration 100% en ligne (e-Estonia)." },
    { "rang": 26, "pays": "Chili", "taux": 92.8, "observations": "Champion d'Amérique latine pour le déploiement fibre." },
    { "rang": 27, "pays": "Italie", "taux": 91.5, "observations": "Croissance portée par les jeunes et le commerce mobile." },
    { "rang": 28, "pays": "Japon", "taux": 91.2, "observations": "Paradoxe : Très connecté mais usage modéré des réseaux." },
    { "rang": 29, "pays": "Pologne", "taux": 89.5, "observations": "Modernisation éclair des infrastructures urbaines." },
    { "rang": 30, "pays": "Argentine", "taux": 88.3, "observations": "Résilience numérique malgré les crises économiques." },
    { "rang": 31, "pays": "Lettonie", "taux": 92.7, "observations": "Numérisation rapide des services publics sur le modèle estonien." },
    { "rang": 32, "pays": "Chine", "taux": 91.6, "observations": "Le géant mondial : +1,3 milliard d'utilisateurs. Mobile à 99%." },
    { "rang": 33, "pays": "Russie", "taux": 91.2, "observations": "Forte connectivité urbaine malgré les sanctions technologiques." },
    { "rang": 34, "pays": "Malte", "taux": 91.1, "observations": "Usage intensif (jeux en ligne et finance)." },
    { "rang": 35, "pays": "Chypre", "taux": 90.8, "observations": "Hub de services pour les expatriés et entreprises tech." },
    { "rang": 36, "pays": "République Tchèque", "taux": 90.5, "observations": "Intégration profonde du e-commerce." },
    { "rang": 37, "pays": "Slovénie", "taux": 90.4, "observations": "Excellente couverture rurale en haut débit." },
    { "rang": 38, "pays": "Uruguay", "taux": 89.9, "observations": "Leader stable d'Amérique du Sud ; plan 'Un ordi par enfant'." },
    { "rang": 40, "pays": "Roumanie", "taux": 89.2, "observations": "Fibre ultra-rapide et parmi les moins chères d'Europe." },
    { "rang": 41, "pays": "Thaïlande", "taux": 89.1, "observations": "Explosion de l'économie des plateformes et paiements mobiles." },
    { "rang": 42, "pays": "Portugal", "taux": 88.7, "observations": "Adoption des visas 'Digital Nomad' boostant la connectivité." },
    { "rang": 43, "pays": "Serbie", "taux": 87.5, "observations": "Hub technologique croissant dans les Balkans." },
    { "rang": 44, "pays": "Monténégro", "taux": 86.9, "observations": "Développement lié au tourisme de luxe." },
    { "rang": 45, "pays": "Brésil", "taux": 85.2, "observations": "Société ultra-sociale : Record de temps passé sur les réseaux." },
    { "rang": 46, "pays": "Slovaquie", "taux": 84.8, "observations": "Rattrapage numérique soutenu par les fonds européens." },
    { "rang": 47, "pays": "Turquie", "taux": 84.1, "observations": "Usage mobile massif et essor des start-ups logistiques." },
    { "rang": 48, "pays": "Mexique", "taux": 83.5, "observations": "Forte croissance portée par la jeunesse (mobile prépayé)." },
    { "rang": 49, "pays": "Grèce", "taux": 82.8, "observations": "Modernisation des îles grâce au satellite et à la 5G." },
    { "rang": 50, "pays": "Bulgarie", "taux": 81.9, "observations": "Très bonne qualité de débit malgré une population vieillissante." },
    { "rang": 51, "pays": "Indonésie", "taux": 80.5, "observations": "230 millions d'utilisateurs. Tout passe par le mobile." },
    { "rang": 52, "pays": "Iran", "taux": 80.2, "observations": "Forte culture numérique malgré les restrictions." },
    { "rang": 53, "pays": "Colombie", "taux": 79.5, "observations": "Accélération du e-commerce et des services publics." },
    { "rang": 54, "pays": "Afrique du Sud", "taux": 78.8, "observations": "Leader du continent en temps passé en ligne." },
    { "rang": 55, "pays": "Vietnam", "taux": 78.2, "observations": "Transformation industrielle vers la tech." },
    { "rang": 56, "pays": "Pérou", "taux": 77.5, "observations": "Rattrapage numérique via l'extension 4G/5G." },
    { "rang": 57, "pays": "Ukraine", "taux": 77.1, "observations": "Résilience numérique incroyable (Starlink, Diia)." },
    { "rang": 58, "pays": "Maroc", "taux": 76.5, "observations": "Pénétration mobile élevée et essor du paiement numérique." },
    { "rang": 59, "pays": "Philippines", "taux": 75.8, "observations": "'Capitale mondiale des réseaux sociaux' (temps passé)." },
    { "rang": 60, "pays": "Algérie", "taux": 74.2, "observations": "Investissements massifs dans la fibre optique." },
    { "rang": 61, "pays": "Inde", "taux": 70.0, "observations": "Saut de géant : +1 milliard d'utilisateurs." },
    { "rang": 62, "pays": "Égypte", "taux": 69.5, "observations": "Transition numérique poussée par une population jeune." },
    { "rang": 63, "pays": "Nigeria", "taux": 68.3, "observations": "Moteur africain : 148 millions d'abonnés." },
    { "rang": 64, "pays": "Tunisie", "taux": 67.8, "observations": "Infrastructure historique et services éducatifs en ligne." },
    { "rang": 65, "pays": "Ouzbékistan", "taux": 67.2, "observations": "Modernisation accélérée depuis l'ouverture." },
    { "rang": 66, "pays": "Équateur", "taux": 66.5, "observations": "Croissance stable portée par les usages mobiles." },
    { "rang": 67, "pays": "Paraguay", "taux": 65.9, "observations": "Expansion de la connectivité dans les zones agricoles." },
    { "rang": 68, "pays": "Ghana", "taux": 65.2, "observations": "Hub de la 'Fintech' en Afrique de l'Ouest." },
    { "rang": 69, "pays": "Bolivie", "taux": 64.8, "observations": "Efforts de désenclavement via satellites." },
    { "rang": 70, "pays": "Salvador", "taux": 64.2, "observations": "Adoption du Bitcoin et digitalisation de l'économie." },
    { "rang": 71, "pays": "Kenya", "taux": 63.5, "observations": "Leader de la 'Silicon Savannah' (M-Pesa)." },
    { "rang": 72, "pays": "Honduras", "taux": 62.1, "observations": "Croissance portée par les transferts de fonds." },
    { "rang": 73, "pays": "Sénégal", "taux": 61.4, "observations": "Dynamisme à Dakar ; fracture rurale persistante." },
    { "rang": 74, "pays": "Nicaragua", "taux": 60.8, "observations": "Domination du prépayé mobile." },
    { "rang": 75, "pays": "Côte d'Ivoire", "taux": 59.7, "observations": "Investissements massifs dans la 4G/5G urbaine." },
    { "rang": 77, "pays": "Guatemala", "taux": 57.5, "observations": "Inégalités fortes entre hauts plateaux et capitale." },
    { "rang": 78, "pays": "Cameroun", "taux": 56.9, "observations": "Développement du e-commerce malgré les coupures." },
    { "rang": 79, "pays": "Angola", "taux": 55.2, "observations": "Marché jeune et urbain actif sur les réseaux sociaux." },
    { "rang": 80, "pays": "Bangladesh", "taux": 54.1, "observations": "Hub tech, mais accès citoyen encore limité." },
    { "rang": 81, "pays": "Pakistan", "taux": 52.8, "observations": "Population immense (~240M) rendant la couverture coûteuse." },
    { "rang": 82, "pays": "Népal", "taux": 51.5, "observations": "Défis topographiques immenses (Himalaya)." },
    { "rang": 83, "pays": "Tanzanie", "taux": 50.2, "observations": "Transition vers une économie de services numériques." },
    { "rang": 84, "pays": "Zambie", "taux": 49.5, "observations": "Porté par le secteur minier et les centres urbains." },
    { "rang": 85, "pays": "Rwanda", "taux": 48.8, "observations": "Modèle de volonté : infrastructures prêtes, coût d'accès élevé." },
    { "rang": 86, "pays": "Cambodge", "taux": 47.5, "observations": "Usage mobile très élevé chez les jeunes urbains." },
    { "rang": 87, "pays": "Ouganda", "taux": 46.2, "observations": "Forte taxation des réseaux sociaux freinant l'usage." },
    { "rang": 88, "pays": "Soudan", "taux": 45.1, "observations": "Infrastructures impactées par les conflits." },
    { "rang": 89, "pays": "Zimbabwe", "taux": 44.5, "observations": "Résilience via les transferts d'argent mobile." },
    { "rang": 90, "pays": "Myanmar", "taux": 43.8, "observations": "Recul lié à l'instabilité et aux coupures d'État." },
    { "rang": 91, "pays": "Yémen", "taux": 42.5, "observations": "Infrastructures détruites et économie de guerre." },
    { "rang": 92, "pays": "Mali", "taux": 41.8, "observations": "Insécurité et vastes zones désertiques." },
    { "rang": 93, "pays": "Togo", "taux": 40.5, "observations": "Coût de la data très élevé." },
    { "rang": 94, "pays": "Bénin", "taux": 39.2, "observations": "Transition numérique centrée sur Cotonou." },
    { "rang": 95, "pays": "Haïti", "taux": 38.5, "observations": "Instabilité politique bloquant les investissements." },
    { "rang": 96, "pays": "Éthiopie", "taux": 37.1, "observations": "Monopole d'État freinant l'accès pour 120M d'habitants." },
    { "rang": 97, "pays": "Mozambique", "taux": 36.4, "observations": "Défis climatiques (cyclones) détruisant les antennes." },
    { "rang": 98, "pays": "Burkina Faso", "taux": 35.8, "observations": "Crise sécuritaire limitant l'entretien des pylônes." },
    { "rang": 99, "pays": "Guinée", "taux": 34.2, "observations": "Richesse minière peu traduite en infrastructures civiles." },
    { "rang": 100, "pays": "Libéria", "taux": 33.5, "observations": "Manque de réseau électrique national." },
    { "rang": 101, "pays": "Afghanistan", "taux": 32.8, "observations": "Restrictions sociales et isolement diplomatique." },
    { "rang": 102, "pays": "Madagascar", "taux": 31.2, "observations": "Isolement rural extrême et coût du matériel." },
    { "rang": 103, "pays": "Tchad", "taux": 30.5, "observations": "Enclavement total et désertification numérique." },
    { "rang": 104, "pays": "Somalie", "taux": 29.8, "observations": "Privé mobile dynamique mais limité géographiquement." },
    { "rang": 105, "pays": "Malawi", "taux": 28.2, "observations": "85% de ruraux en agriculture de subsistance." },
    { "rang": 106, "pays": "RD Congo", "taux": 27.5, "observations": "Géant déconnecté : Immensité de la jungle vs peu de câbles." },
    { "rang": 107, "pays": "Sierra Leone", "taux": 26.1, "observations": "Électricité rare en dehors de Freetown." },
    { "rang": 108, "pays": "Niger", "taux": 25.4, "observations": "Un des taux d'urbanisation les plus bas au monde." },
    { "rang": 109, "pays": "Soudan du Sud", "taux": 24.8, "observations": "Infrastructures en construction." },
    { "rang": 110, "pays": "Turkménistan", "taux": 22.1, "observations": "Accès restreint par l'État et prix prohibitifs." },
    { "rang": 111, "pays": "Érythrée", "taux": 20.5, "observations": "Contrôle total et pénuries d'énergie." },
    { "rang": 112, "pays": "Burundi", "taux": 19.2, "observations": "Pauvreté extrême bloquant l'équipement." },
    { "rang": 113, "pays": "Centrafrique", "taux": 18.5, "observations": "Zones blanches massives dues à l'instabilité." },
    { "rang": 114, "pays": "Corée du Nord", "taux": 0.1, "observations": "Intranet national uniquement (Kwangmyong)." }
  ]
}